langchain_agent_protocol/__init__.py
langchain_agent_protocol/adapters/__init__.py
langchain_agent_protocol/adapters/openai_adapter.py
langchain_agent_protocol/converters/__init__.py
langchain_agent_protocol/converters/message_converter.py
langchain_agent_protocol/core/__init__.py
langchain_agent_protocol/core/agent.py
langchain_agent_protocol/core/base_llm_adapter.py
langchain_agent_protocol/core/config.py
langchain_agent_protocol/parsers/__init__.py
langchain_agent_protocol/parsers/tool_call_parser.py
langchain_agent_protocol/processors/__init__.py
langchain_agent_protocol/processors/stream_processor.py
langchain_agent_protocol-0.2.0.dist-info/licenses/LICENSE
langchain_agent_protocol-0.2.0.dist-info/METADATA
langchain_agent_protocol-0.2.0.dist-info/WHEEL
langchain_agent_protocol-0.2.0.dist-info/top_level.txt
langchain_agent_protocol-0.2.0.dist-info/RECORD
