Metadata-Version: 2.4
Name: langchain-agent-protocol
Version: 0.2.0
Summary: A universal, framework-agnostic LangChain Agent protocol for cross-project portability
Author-email: Tuple <wzw571603974@qq.com>
License: MIT
Project-URL: Homepage, https://github.com/SunshineList/langchain-agent-protocol
Project-URL: Documentation, https://langchain-agent-protocol.readthedocs.io
Project-URL: Repository, https://github.com/SunshineList/langchain-agent-protocol
Project-URL: Bug Tracker, https://github.com/SunshineList/langchain-agent-protocol/issues
Keywords: langchain,agent,llm,ai,chatbot,protocol
Classifier: Development Status :: 3 - Alpha
Classifier: Intended Audience :: Developers
Classifier: License :: OSI Approved :: MIT License
Classifier: Programming Language :: Python :: 3
Classifier: Programming Language :: Python :: 3.8
Classifier: Programming Language :: Python :: 3.9
Classifier: Programming Language :: Python :: 3.10
Classifier: Programming Language :: Python :: 3.11
Classifier: Programming Language :: Python :: 3.12
Classifier: Programming Language :: Python :: 3.13
Classifier: Topic :: Software Development :: Libraries :: Python Modules
Requires-Python: >=3.8
License-File: LICENSE
Requires-Dist: langchain-core>=0.1.0
Requires-Dist: pydantic>=2.0.0
Provides-Extra: dev
Requires-Dist: pytest>=7.0.0; extra == "dev"
Requires-Dist: pytest-asyncio>=0.21.0; extra == "dev"
Requires-Dist: black>=23.0.0; extra == "dev"
Requires-Dist: isort>=5.12.0; extra == "dev"
Requires-Dist: mypy>=1.0.0; extra == "dev"
Provides-Extra: openai
Requires-Dist: openai>=1.0.0; extra == "openai"
Provides-Extra: anthropic
Requires-Dist: anthropic>=0.18.0; extra == "anthropic"
Provides-Extra: all
Requires-Dist: langchain-agent-protocol[anthropic,openai]; extra == "all"
Dynamic: license-file
